<?xml version="1.0"?>
<opencv_storage>
<calibration_time>"Tue Dec 13 11:20:55 2022"</calibration_time>
<nr_of_frames>15</nr_of_frames>
<image_width>1280</image_width>
<image_height>720</image_height>
<board_width>7</board_width>
<board_height>5</board_height>
<square_size>4.1299999237060547e+01</square_size>
<fix_aspect_ratio>1.</fix_aspect_ratio>
<!-- flags: +fix_aspectRatio +fix_principal_point +zero_tangent_dist -->
<flags>14</flags>
<fisheye_model>0</fisheye_model>
<camera_matrix type_id="opencv-matrix">
  <rows>3</rows>
  <cols>3</cols>
  <dt>d</dt>
  <data>
    8.4853117539872062e+02 0. 6.3950000000000000e+02 0.
    8.4853117539872062e+02 3.5950000000000000e+02 0. 0. 1.</data></camera_matrix>
<distortion_coefficients type_id="opencv-matrix">
  <rows>5</rows>
  <cols>1</cols>
  <dt>d</dt>
  <data>
    1.5971715887123378e-01 -6.1045779426294378e-01 0. 0.
    8.5262249761470854e-01</data></distortion_coefficients>
<avg_reprojection_error>5.2874946538704726e-01</avg_reprojection_error>
<per_view_reprojection_errors type_id="opencv-matrix">
  <rows>15</rows>
  <cols>1</cols>
  <dt>f</dt>
  <data>
    4.49106157e-01 5.81236362e-01 5.42254686e-01 7.86455929e-01
    3.29543382e-01 8.00300241e-01 5.48311293e-01 5.27014315e-01
    6.35177612e-01 5.84983468e-01 4.89403009e-01 3.12290341e-01
    3.85835439e-01 2.76470512e-01 3.25706035e-01</data></per_view_reprojection_errors>
<!-- a set of 6-tuples (rotation vector + translation vector) for each view -->
<extrinsic_parameters type_id="opencv-matrix">
  <rows>15</rows>
  <cols>6</cols>
  <dt>d</dt>
  <data>
    -6.0554652109577584e-02 3.2691526552001132e-01
    3.5526466939370166e-01 -1.6971723464308741e+02
    -1.6766319136242126e+02 5.5564934272073344e+02
    -2.8331620017182282e-02 9.6416996845140712e-01
    1.7184262358982805e-01 3.9292745243457276e+01
    -1.2570307344423776e+02 6.3942778919121997e+02
    2.8762252907124525e-01 -7.8930408613513392e-01
    -1.3014416620314589e-01 -3.0654946781201772e+02
    1.0484140054674683e+01 5.1358144082819069e+02
    -9.7742453693133599e-02 -7.5924449579177100e-01
    1.8256149290276455e-01 -9.2482554142518993e+01
    -8.1114722284353249e+01 3.8837144073963316e+02
    2.5755096493992441e-01 -8.0294009092010321e-01
    -9.6533967521763422e-02 -2.6970205063551697e+02
    2.5589239751002982e+01 5.0783715062318799e+02
    -1.7843005638349671e-01 1.9341002499430987e-01
    -1.3519792498710984e-01 -8.1036215482681200e+01
    -6.6323033350371588e+01 5.4580717985991294e+02
    -1.3288519999777348e-01 6.1027037352174496e-01
    -9.6585706085635367e-02 1.8277815444832786e+01
    -5.8980946164709287e+01 6.5312603566061978e+02
    -1.4154305338007866e-01 6.5928306163386807e-01
    -9.8098601895930240e-02 -1.3412521678592778e+01
    -4.6705619193251898e+01 6.9094611491404271e+02
    -7.3733973850107312e-02 7.7618459873084145e-01
    -8.0173231308532031e-02 -1.1522832804401536e+02
    -7.0665787583096531e+01 6.0264105544203665e+02
    -6.7453229591820277e-02 8.6410410905354540e-01
    -4.3869105193633219e-02 -7.7468031631536832e+01
    -8.0881066901623441e+01 6.1161133902183212e+02
    -2.0629918923733389e-02 8.3898435069912869e-01
    -5.1089531932839480e-02 -9.1919384296811529e+01
    -8.6984879570404814e+01 6.0126960210501306e+02
    2.6300011126420264e-01 5.9771329096487136e-01
    -2.8795500626360441e-02 -1.7888371262031464e+02
    -1.1303604649561566e+02 6.0988780547921226e+02
    6.0344968108306429e-01 6.1651141840644674e-01
    -8.0690664435351875e-02 -1.6251826747292279e+02
    -9.6553497951523781e+01 5.9327866301771280e+02
    6.0148434598007849e-01 6.7190182291534650e-01
    -9.3641973346915680e-02 -1.5310072694368861e+02
    -8.9073104043774904e+01 5.9765847929581150e+02
    7.1959506623166247e-01 8.3071905325883433e-01
    -1.1681201601297077e-01 -1.5821130895289801e+02
    -8.4698844568540366e+01 5.3056799955035467e+02</data></extrinsic_parameters>
<image_points type_id="opencv-matrix">
  <rows>15</rows>
  <cols>35</cols>
  <dt>"2f"</dt>
  <data>
    3.77561829e+02 1.00252731e+02 4.28601898e+02 1.15506355e+02
    4.82650909e+02 1.31662750e+02 5.39591919e+02 1.49236282e+02
    5.99211731e+02 1.67415085e+02 6.61917664e+02 1.86591370e+02
    7.27833252e+02 2.06292282e+02 3.54726501e+02 1.59626114e+02
    4.05727997e+02 1.76704620e+02 4.59548523e+02 1.94569504e+02
    5.16078125e+02 2.13706161e+02 5.75347961e+02 2.33623779e+02
    6.37139954e+02 2.54307297e+02 7.02264954e+02 2.75866272e+02
    3.32468964e+02 2.19569870e+02 3.82677460e+02 2.37969421e+02
    4.36049744e+02 2.57435059e+02 4.92295441e+02 2.77945465e+02
    5.51032837e+02 2.99246552e+02 6.12415100e+02 3.21506439e+02
    6.76731812e+02 3.44665283e+02 3.09678772e+02 2.79402161e+02
    3.59498047e+02 2.99320648e+02 4.12388092e+02 3.20216797e+02
    4.68078369e+02 3.41947113e+02 5.26448730e+02 3.64831787e+02
    5.87327515e+02 3.88748596e+02 6.51024963e+02 4.13948639e+02
    2.86882294e+02 3.39306000e+02 3.36404388e+02 3.60717468e+02
    3.88474304e+02 3.82968872e+02 4.43467377e+02 4.06554382e+02
    5.01322571e+02 4.30839508e+02 5.61744141e+02 4.56713348e+02
    6.25427063e+02 4.83835999e+02 6.92710815e+02 1.92427155e+02
    7.27850830e+02 1.90576706e+02 7.67271057e+02 1.88389542e+02
    8.11934509e+02 1.85981979e+02 8.62528442e+02 1.83139832e+02
    9.21313782e+02 1.80206924e+02 9.88522644e+02 1.76856384e+02
    6.83357056e+02 2.46661179e+02 7.17931274e+02 2.48296692e+02
    7.56635620e+02 2.49414749e+02 8.00529419e+02 2.51148773e+02
    8.50658813e+02 2.52674423e+02 9.08171448e+02 2.54723114e+02
    9.74541626e+02 2.57288910e+02 6.74481445e+02 3.00731201e+02
    7.08251587e+02 3.05147827e+02 7.46179810e+02 3.10025513e+02
    7.88986023e+02 3.15442871e+02 8.38400818e+02 3.21633606e+02
    8.95228455e+02 3.28775116e+02 9.60375122e+02 3.37070129e+02
    6.65341980e+02 3.54334656e+02 6.98535461e+02 3.61685883e+02
    7.36035217e+02 3.70103668e+02 7.78178772e+02 3.79485657e+02
    8.26432495e+02 3.90177338e+02 8.82236084e+02 4.02438141e+02
    9.46347107e+02 4.16665436e+02 6.56243591e+02 4.07840454e+02
    6.89116211e+02 4.18363464e+02 7.25838684e+02 4.30104340e+02
    7.67297058e+02 4.43400085e+02 8.14776672e+02 4.58557678e+02
    8.69623352e+02 4.76091034e+02 9.32557312e+02 4.95914062e+02
    1.25079781e+02 3.77049622e+02 1.97863556e+02 3.61830811e+02
    2.64262421e+02 3.47914062e+02 3.23542175e+02 3.35526733e+02
    3.77598724e+02 3.24120667e+02 4.26809570e+02 3.13598572e+02
    4.72370087e+02 3.04248657e+02 1.37274689e+02 4.41199677e+02
    2.08243866e+02 4.22690002e+02 2.72631165e+02 4.05839691e+02
    3.30430756e+02 3.90847870e+02 3.83060211e+02 3.77191895e+02
    4.31580780e+02 3.64627655e+02 4.75944733e+02 3.52952301e+02
    1.48883896e+02 5.02246277e+02 2.17770218e+02 4.81245972e+02
    2.80605713e+02 4.61815582e+02 3.36923157e+02 4.44641510e+02
    3.88579803e+02 4.28517426e+02 4.35898346e+02 4.13836487e+02
    4.79637115e+02 4.00391083e+02 1.60018250e+02 5.61113647e+02
    2.26936035e+02 5.37508179e+02 2.88020142e+02 5.15667603e+02
    3.43497101e+02 4.96100433e+02 3.93807037e+02 4.78241180e+02
    4.40145477e+02 4.61553650e+02 4.82909454e+02 4.46312531e+02
    1.71414764e+02 6.17304810e+02 2.35613907e+02 5.91612793e+02
    2.95439056e+02 5.67580811e+02 3.49671539e+02 5.45836792e+02
    3.99013306e+02 5.26260315e+02 4.44178314e+02 5.08134033e+02
    4.86046967e+02 4.91049438e+02 4.35809357e+02 1.81131927e+02
    5.10654083e+02 2.10598373e+02 5.75420898e+02 2.36272079e+02
    6.31800293e+02 2.58606354e+02 6.81809937e+02 2.78155182e+02
    7.25899658e+02 2.95491547e+02 7.66526794e+02 3.11340759e+02
    4.20662323e+02 2.68222565e+02 4.97680756e+02 2.92218140e+02
    5.64176819e+02 3.12626892e+02 6.22010010e+02 3.30344208e+02
    6.73118835e+02 3.46095642e+02 7.18777405e+02 3.60069794e+02
    7.59769226e+02 3.72753784e+02 4.04007233e+02 3.58687134e+02
    4.83790436e+02 3.76188965e+02 5.52519043e+02 3.91225800e+02
    6.12175110e+02 4.04437744e+02 6.64675232e+02 4.16124176e+02
    7.11365723e+02 4.26527863e+02 7.53557922e+02 4.35984589e+02
    3.86454102e+02 4.52691467e+02 4.68752960e+02 4.63748810e+02
    5.39721252e+02 4.73081390e+02 6.01560181e+02 4.81390930e+02
    6.55769409e+02 4.88645905e+02 7.03760437e+02 4.95502014e+02
    7.47312195e+02 5.01613892e+02 3.68421326e+02 5.50811462e+02
    4.52996552e+02 5.55254272e+02 5.26443298e+02 5.58693848e+02
    5.90420471e+02 5.61757263e+02 6.46623413e+02 5.64615906e+02
    6.96197327e+02 5.67260742e+02 7.40628357e+02 5.69550720e+02
    1.82025513e+02 4.02934998e+02 2.53395645e+02 3.88519684e+02
    3.16777771e+02 3.75692047e+02 3.74044342e+02 3.64137512e+02
    4.26295929e+02 3.53435089e+02 4.73300018e+02 3.43906555e+02
    5.16623047e+02 3.35079071e+02 1.90582657e+02 4.67960663e+02
    2.59954773e+02 4.50457428e+02 3.22041443e+02 4.34517395e+02
    3.77962128e+02 4.20204132e+02 4.28999847e+02 4.07023590e+02
    4.75617554e+02 3.95052795e+02 5.17857605e+02 3.84101379e+02
    1.98499069e+02 5.30635315e+02 2.66354156e+02 5.09986176e+02
    3.27322937e+02 4.91407166e+02 3.81932556e+02 4.74563080e+02
    4.31926300e+02 4.59113861e+02 4.77545929e+02 4.44872223e+02
    5.19410828e+02 4.31875702e+02 2.06156479e+02 5.91020569e+02
    2.72301300e+02 5.67554993e+02 3.31803162e+02 5.46360168e+02
    3.85661224e+02 5.27131287e+02 4.34638519e+02 5.09598541e+02
    4.79373474e+02 4.93360413e+02 5.20592407e+02 4.78480804e+02
    2.14032150e+02 6.49136597e+02 2.77815826e+02 6.23312866e+02
    3.36410980e+02 5.99389099e+02 3.89293457e+02 5.78154968e+02
    4.37353729e+02 5.58615234e+02 4.81219177e+02 5.40718384e+02
    5.21630066e+02 5.24039185e+02 5.13892639e+02 2.55297333e+02
    5.75473206e+02 2.44201065e+02 6.38656860e+02 2.32748169e+02
    7.03488159e+02 2.20913834e+02 7.70488159e+02 2.08225723e+02
    8.40088989e+02 1.95419510e+02 9.11828552e+02 1.81864456e+02
    5.19510559e+02 3.17477081e+02 5.82401611e+02 3.07308014e+02
    6.46532654e+02 2.96424377e+02 7.12339111e+02 2.85511383e+02
    7.80597229e+02 2.73947357e+02 8.51547058e+02 2.61651886e+02
    9.24772705e+02 2.49293030e+02 5.25375061e+02 3.81742249e+02
    5.89141602e+02 3.72171692e+02 6.54457275e+02 3.61921570e+02
    7.21541565e+02 3.51793030e+02 7.91149475e+02 3.41128784e+02
    8.63526794e+02 3.30319916e+02 9.38573364e+02 3.18662628e+02
    5.30922607e+02 4.48278961e+02 5.95849976e+02 4.39199890e+02
    6.62562439e+02 4.29854492e+02 7.31290344e+02 4.20585510e+02
    8.02221191e+02 4.10907379e+02 8.76342957e+02 4.01158173e+02
    9.52593750e+02 3.90698303e+02 5.36365906e+02 5.17582886e+02
    6.02945496e+02 5.09311829e+02 6.71007629e+02 5.00656342e+02
    7.41375427e+02 4.92291382e+02 8.14252991e+02 4.83707336e+02
    8.89649048e+02 4.75091125e+02 9.67404724e+02 4.65480988e+02
    6.63847168e+02 2.82438049e+02 7.10046021e+02 2.72351929e+02
    7.60013550e+02 2.61399475e+02 8.14372742e+02 2.49503082e+02
    8.73501953e+02 2.36470123e+02 9.37777893e+02 2.22631958e+02
    1.00777814e+03 2.07475891e+02 6.66436218e+02 3.34975342e+02
    7.13476624e+02 3.26946594e+02 7.64218079e+02 3.17989471e+02
    8.19233765e+02 3.08583008e+02 8.79510376e+02 2.98118408e+02
    9.45022156e+02 2.86611542e+02 1.01633392e+03 2.74285126e+02
    6.69523743e+02 3.88899597e+02 7.16838501e+02 3.82623016e+02
    7.68319153e+02 3.76100739e+02 8.24411926e+02 3.68811676e+02
    8.85842285e+02 3.60998932e+02 9.52579285e+02 3.52518341e+02
    1.02509131e+03 3.42976105e+02 6.72267212e+02 4.44270294e+02
    7.20470703e+02 4.40154388e+02 7.72870911e+02 4.35642883e+02
    8.29931641e+02 4.31152618e+02 8.92312012e+02 4.25804535e+02
    9.60240112e+02 4.20165344e+02 1.03429785e+03 4.13662140e+02
    6.75128967e+02 5.01380493e+02 7.24372375e+02 4.99392883e+02
    7.77697266e+02 4.97367004e+02 8.35814514e+02 4.95217987e+02
    8.99032532e+02 4.92739868e+02 9.68154053e+02 4.89833649e+02
    1.04366858e+03 4.86728699e+02 6.23610474e+02 3.01752899e+02
    6.64363037e+02 2.92609192e+02 7.08103638e+02 2.82613220e+02
    7.55511841e+02 2.71814362e+02 8.07310242e+02 2.59972687e+02
    8.64301331e+02 2.47016220e+02 9.26234619e+02 2.32817276e+02
    6.25438904e+02 3.51477875e+02 6.66720703e+02 3.44214447e+02
    7.11345215e+02 3.36108856e+02 7.59484863e+02 3.27482697e+02
    8.12260864e+02 3.17902191e+02 8.69922119e+02 3.07543701e+02
    9.33263794e+02 2.96224304e+02 6.27489136e+02 4.02586121e+02
    6.69308228e+02 3.96913452e+02 7.14582764e+02 3.90884399e+02
    7.63488159e+02 3.84436066e+02 8.17282410e+02 3.77412354e+02
    8.75962219e+02 3.69615753e+02 9.40421570e+02 3.61092499e+02
    6.29388367e+02 4.55117432e+02 6.71835693e+02 4.51393921e+02
    7.17764038e+02 4.47312683e+02 7.67689026e+02 4.43195801e+02
    8.22526611e+02 4.38666565e+02 8.82447754e+02 4.33773407e+02
    9.47802551e+02 4.28307556e+02 6.31263062e+02 5.09291809e+02
    6.74661987e+02 5.07473755e+02 7.21443237e+02 5.05655518e+02
    7.72422180e+02 5.03860077e+02 8.28053772e+02 5.02171661e+02
    8.89125244e+02 4.99967560e+02 9.55593018e+02 4.97464020e+02
    4.76841980e+02 2.59155640e+02 5.12324463e+02 2.48282898e+02
    5.51378967e+02 2.36225266e+02 5.94749756e+02 2.22924088e+02
    6.42692505e+02 2.07764893e+02 6.97592529e+02 1.90524033e+02
    7.59474182e+02 1.70864838e+02 4.78070038e+02 3.16725433e+02
    5.14384277e+02 3.08702209e+02 5.53826965e+02 2.99794403e+02
    5.97751404e+02 2.89734467e+02 6.46718994e+02 2.78586945e+02
    7.01639160e+02 2.65710266e+02 7.64637634e+02 2.51186066e+02
    4.79742096e+02 3.75524689e+02 5.16103088e+02 3.70016479e+02
    5.56122131e+02 3.64318390e+02 6.00591064e+02 3.57552856e+02
    6.50044922e+02 3.50230957e+02 7.06110413e+02 3.41960815e+02
    7.69725769e+02 3.32517639e+02 4.80811310e+02 4.35281464e+02
    5.17461853e+02 4.32819122e+02 5.58331055e+02 4.30042847e+02
    6.03180237e+02 4.26947205e+02 6.53536804e+02 4.23468811e+02
    7.10587402e+02 4.19883423e+02 7.75259399e+02 4.15879669e+02
    4.81623932e+02 4.96551422e+02 5.19028931e+02 4.97114380e+02
    5.60153320e+02 4.97574921e+02 6.05739624e+02 4.98442841e+02
    6.57080566e+02 4.99405365e+02 7.15183899e+02 5.00646545e+02
    7.81408569e+02 5.02470642e+02 5.32431335e+02 2.46662003e+02
    5.65519470e+02 2.36752991e+02 6.02627930e+02 2.25795532e+02
    6.44272217e+02 2.13269501e+02 6.90830505e+02 1.99085052e+02
    7.45063660e+02 1.82472641e+02 8.06828186e+02 1.63548523e+02
    5.31992859e+02 3.03502258e+02 5.65929565e+02 2.96671478e+02
    6.03275024e+02 2.89053101e+02 6.45265259e+02 2.80351471e+02
    6.92616211e+02 2.70391479e+02 7.46642212e+02 2.58862946e+02
    8.09346436e+02 2.45574356e+02 5.32283203e+02 3.61227295e+02
    5.65883240e+02 3.57276306e+02 6.03561157e+02 3.52966675e+02
    6.45801147e+02 3.47824829e+02 6.93592529e+02 3.42427399e+02
    7.48485229e+02 3.36077148e+02 8.11446960e+02 3.28680756e+02
    5.31604126e+02 4.19521790e+02 5.65710266e+02 4.18718384e+02
    6.03985352e+02 4.17815887e+02 6.46598328e+02 4.16819366e+02
    6.94916443e+02 4.15633484e+02 7.50501099e+02 4.14657837e+02
    8.14366211e+02 4.13434509e+02 5.30977295e+02 4.79390381e+02
    5.65712769e+02 4.81591339e+02 6.04263306e+02 4.84414276e+02
    6.47331787e+02 4.87417999e+02 6.96272095e+02 4.91062225e+02
    7.52662292e+02 4.95439789e+02 8.17740967e+02 5.00721344e+02
    5.09831329e+02 2.35889725e+02 5.43719482e+02 2.26136063e+02
    5.81551086e+02 2.15433960e+02 6.23905212e+02 2.03086349e+02
    6.71544067e+02 1.89089828e+02 7.26489990e+02 1.72760315e+02
    7.89577820e+02 1.54163879e+02 5.11052429e+02 2.94190460e+02
    5.45790466e+02 2.87539429e+02 5.84063354e+02 2.80088806e+02
    6.26713501e+02 2.71772003e+02 6.74818115e+02 2.62242920e+02
    7.29583130e+02 2.51178391e+02 7.93255981e+02 2.38267471e+02
    5.13451904e+02 3.52709778e+02 5.47621094e+02 3.49103546e+02
    5.86141174e+02 3.45152191e+02 6.29054932e+02 3.40479034e+02
    6.77511658e+02 3.35272064e+02 7.32951416e+02 3.29371246e+02
    7.97025085e+02 3.22590332e+02 5.14538513e+02 4.11652039e+02
    5.49365906e+02 4.11368561e+02 5.88284729e+02 4.10573273e+02
    6.31616150e+02 4.10006134e+02 6.80446716e+02 4.09361633e+02
    7.36556152e+02 4.08571960e+02 8.01046509e+02 4.07741699e+02
    5.15849060e+02 4.71639801e+02 5.51158264e+02 4.74339386e+02
    5.90357361e+02 4.77103180e+02 6.34016724e+02 4.80676971e+02
    6.83634644e+02 4.84582947e+02 7.40431030e+02 4.89052734e+02
    8.06107300e+02 4.94883942e+02 3.88339355e+02 2.00191162e+02
    4.28084381e+02 1.97096985e+02 4.71561584e+02 1.93834579e+02
    5.18585510e+02 1.90446655e+02 5.69400757e+02 1.86601044e+02
    6.25328064e+02 1.82099808e+02 6.86044434e+02 1.77059097e+02
    3.97837494e+02 2.58153625e+02 4.37991058e+02 2.57316254e+02
    4.81286438e+02 2.56432129e+02 5.27861450e+02 2.55580261e+02
    5.78427429e+02 2.54545166e+02 6.33047058e+02 2.53335129e+02
    6.93208801e+02 2.51540909e+02 4.07604980e+02 3.13982208e+02
    4.47427277e+02 3.15363556e+02 4.90211823e+02 3.16756500e+02
    5.36548340e+02 3.18366180e+02 5.86379883e+02 3.19527069e+02
    6.40376404e+02 3.21274567e+02 6.99300781e+02 3.22800354e+02
    4.16976959e+02 3.68421051e+02 4.56404938e+02 3.71596375e+02
    4.98964233e+02 3.74785797e+02 5.44500061e+02 3.78584625e+02
    5.93691040e+02 3.82426727e+02 6.47329712e+02 3.86601105e+02
    7.05356750e+02 3.91215485e+02 4.25520111e+02 4.21254456e+02
    4.65003632e+02 4.26018097e+02 5.07180908e+02 4.31265900e+02
    5.52399109e+02 4.37177643e+02 6.00966736e+02 4.43296082e+02
    6.53943481e+02 4.49985291e+02 7.11569519e+02 4.57431000e+02
    4.04472931e+02 2.19386505e+02 4.45941437e+02 2.20455429e+02
    4.91146118e+02 2.21812088e+02 5.40115173e+02 2.22990387e+02
    5.92863647e+02 2.24490982e+02 6.51282410e+02 2.25698547e+02
    7.14633240e+02 2.26753189e+02 4.26572632e+02 2.72033386e+02
    4.67977692e+02 2.75058563e+02 5.12425598e+02 2.78540771e+02
    5.60118774e+02 2.82055939e+02 6.11776123e+02 2.85541626e+02
    6.67945862e+02 2.89692627e+02 7.29677429e+02 2.93406403e+02
    4.48229340e+02 3.21200653e+02 4.88463806e+02 3.26038666e+02
    5.31856445e+02 3.31104950e+02 5.78395325e+02 3.36391235e+02
    6.28683594e+02 3.41790070e+02 6.83406067e+02 3.47811829e+02
    7.43174622e+02 3.54578400e+02 4.67455109e+02 3.66867157e+02
    5.07293640e+02 3.73260712e+02 5.49824158e+02 3.79674164e+02
    5.95478760e+02 3.86681335e+02 6.44430420e+02 3.93879852e+02
    6.97806641e+02 4.02192139e+02 7.55821289e+02 4.11156464e+02
    4.85658295e+02 4.10235016e+02 5.24634521e+02 4.17275269e+02
    5.66558167e+02 4.25322357e+02 6.10830872e+02 4.33584290e+02
    6.58942688e+02 4.42825256e+02 7.11149841e+02 4.52590271e+02
    7.67985474e+02 4.63503143e+02 4.19952118e+02 2.31438644e+02
    4.59246643e+02 2.32912674e+02 5.01827850e+02 2.34539398e+02
    5.48473206e+02 2.35884537e+02 5.99289917e+02 2.37680923e+02
    6.55733459e+02 2.38983353e+02 7.18135437e+02 2.40550308e+02
    4.42705048e+02 2.83364929e+02 4.81861572e+02 2.86683777e+02
    5.24145691e+02 2.90472076e+02 5.69711670e+02 2.94408325e+02
    6.19696960e+02 2.98422821e+02 6.74350769e+02 3.02895111e+02
    7.35234497e+02 3.07463501e+02 4.64570801e+02 3.31529968e+02
    5.02865204e+02 3.36745056e+02 5.44379578e+02 3.42361267e+02
    5.89131897e+02 3.48333221e+02 6.38003601e+02 3.54507660e+02
    6.91491882e+02 3.61506561e+02 7.50654968e+02 3.69446228e+02
    4.84438690e+02 3.76634918e+02 5.22238464e+02 3.83516998e+02
    5.63106995e+02 3.90505066e+02 6.07099670e+02 3.98361511e+02
    6.54797424e+02 4.06744659e+02 7.07397156e+02 4.15941956e+02
    7.65121643e+02 4.26521973e+02 5.02973969e+02 4.19355927e+02
    5.40494385e+02 4.27287109e+02 5.80505066e+02 4.35866577e+02
    6.23659973e+02 4.45449829e+02 6.70606323e+02 4.55680634e+02
    7.22376404e+02 4.67116486e+02 7.78827209e+02 4.79566101e+02
    3.84022339e+02 2.22433899e+02 4.17165710e+02 2.27127747e+02
    4.54705505e+02 2.32396439e+02 4.97435089e+02 2.38345596e+02
    5.45493286e+02 2.45180313e+02 6.01358582e+02 2.52222977e+02
    6.65393188e+02 2.60609253e+02 4.17410889e+02 2.76754761e+02
    4.51757721e+02 2.84298706e+02 4.89794373e+02 2.92578766e+02
    5.32321594e+02 3.01695801e+02 5.80412354e+02 3.11797577e+02
    6.34718689e+02 3.23570496e+02 6.98096863e+02 3.36628693e+02
    4.49446808e+02 3.26867676e+02 4.83281189e+02 3.36521149e+02
    5.21349426e+02 3.47472198e+02 5.63531860e+02 3.59293640e+02
    6.11178345e+02 3.72433777e+02 6.65054260e+02 3.87460205e+02
    7.26671021e+02 4.05042999e+02 4.78051575e+02 3.72819153e+02
    5.11979889e+02 3.84560913e+02 5.49626831e+02 3.96882172e+02
    5.91808655e+02 4.11520966e+02 6.38805969e+02 4.27604095e+02
    6.92215881e+02 4.45490234e+02 7.52829407e+02 4.66591248e+02
    5.04482239e+02 4.15642639e+02 5.38658447e+02 4.28670624e+02
    5.76027466e+02 4.43304169e+02 6.17802124e+02 4.59942322e+02
    6.64296387e+02 4.78257050e+02 7.17267456e+02 4.98828003e+02
    7.76621826e+02 5.22387939e+02</data></image_points>
<grid_points>
  0. 0. 0. 4.12999992e+01 0. 0. 8.25999985e+01 0. 0. 1.23899994e+02 0.
  0. 1.65199997e+02 0. 0. 2.06500000e+02 0. 0. 2.47799988e+02 0. 0. 0.
  4.12999992e+01 0. 4.12999992e+01 4.12999992e+01 0. 8.25999985e+01
  4.12999992e+01 0. 1.23899994e+02 4.12999992e+01 0. 1.65199997e+02
  4.12999992e+01 0. 2.06500000e+02 4.12999992e+01 0. 2.47799988e+02
  4.12999992e+01 0. 0. 8.25999985e+01 0. 4.12999992e+01 8.25999985e+01
  0. 8.25999985e+01 8.25999985e+01 0. 1.23899994e+02 8.25999985e+01 0.
  1.65199997e+02 8.25999985e+01 0. 2.06500000e+02 8.25999985e+01 0.
  2.47799988e+02 8.25999985e+01 0. 0. 1.23899994e+02 0. 4.12999992e+01
  1.23899994e+02 0. 8.25999985e+01 1.23899994e+02 0. 1.23899994e+02
  1.23899994e+02 0. 1.65199997e+02 1.23899994e+02 0. 2.06500000e+02
  1.23899994e+02 0. 2.47799988e+02 1.23899994e+02 0. 0. 1.65199997e+02
  0. 4.12999992e+01 1.65199997e+02 0. 8.25999985e+01 1.65199997e+02 0.
  1.23899994e+02 1.65199997e+02 0. 1.65199997e+02 1.65199997e+02 0.
  2.06500000e+02 1.65199997e+02 0. 2.47799988e+02 1.65199997e+02 0.</grid_points>
</opencv_storage>
